{"1073350324":{"data":{"site":{"siteMetadata":{"title":"release: canary","author":{"name":"박진이","social":{"github":"https://github.com/jinnypark9393"}}}}}},"1956554647":{"data":{"allMarkdownRemark":{"edges":[{"node":{"frontmatter":{"title":"Gatsby 테마로 GitHub Blog 만들기","categories":"블로그 featured"},"fields":{"slug":"/gatsby-github-blog/"}}},{"node":{"frontmatter":{"title":"쉽고 빠르게 나만의 개츠비(Gatsby) 블로그 만들기","categories":"블로그 featured"},"fields":{"slug":"/gatsby-starter-zoomkoding-introduction/"}}}]}}},"2938748437":{"data":{"site":{"siteMetadata":{"title":"release: canary","description":"어쩌다 데브옵스 엔지니어가 된 문과생의 기록용 블로그","author":{"name":"박진이"},"ogImage":"/og-image.png"}}}}}